CHANGELOG.rst
LICENSE
MANIFEST.in
NOTICE
README.rst
setup.py
instructions/__init__.py
instructions/compat.py
instructions/exceptions.py
instructions/filters.py
instructions/version.py
instructions.egg-info/PKG-INFO
instructions.egg-info/SOURCES.txt
instructions.egg-info/dependency_links.txt
instructions.egg-info/not-zip-safe
instructions.egg-info/top_level.txt
instructions/commands/__init__.py
instructions/commands/compounds.py
instructions/commands/prototypes.py
instructions/datatypes/__init__.py
instructions/datatypes/python.py