Metadata-Version: 1.1
Name: instructions
Version: 0.1.0
Summary: Working with iterable data structures made easy
Home-page: https://github.com/maxtepkeev/instructions
Author: Max Tepkeev
Author-email: tepkeev@gmail.com
License: Copyright 2015 Max Tepkeev
